swigex0/__init__.py
swigex0/_swigex0.pyd
swigex0/version.py
swigex0-0.3.7.dist-info/METADATA
swigex0-0.3.7.dist-info/WHEEL
swigex0-0.3.7.dist-info/top_level.txt
swigex0-0.3.7.dist-info/RECORD
