Metadata-Version: 2.4
Name: swigex0
Version: 0.3.7
Summary: C++ library and SWIG wrappers (R & Python)
Author-email: Fabien Ors <fabien.ors@minesparis.psl.eu>
License: BSD-3-Clause
Project-URL: Homepage, https://github.com/fabien-ors/swigex0
Project-URL: Issues, https://github.com/fabien-ors/swigex0/issues
Platform: Windows
Platform: Linux
Platform: Mac OS-X
Classifier: Programming Language :: Python :: 3
Classifier: Programming Language :: C++
Classifier: Development Status :: 4 - Beta
Classifier: Environment :: Other Environment
Classifier: Intended Audience :: Developers
Classifier: License :: OSI Approved :: MIT License
Classifier: Operating System :: OS Independent
Classifier: Topic :: Software Development :: Libraries :: Python Modules
Requires-Python: >=3.8
Requires-Dist: numpy<3,>=1.24
